COPYING
COPYING.LESSER
ChangeLog
MANIFEST.in
README
setup.py
./__init__.py
./__pkginfo__.py
./_exceptions.py
./_nodes_ast.py
./as_string.py
./bases.py
./builder.py
./inference.py
./inspector.py
./manager.py
./mixins.py
./node_classes.py
./nodes.py
./protocols.py
./raw_building.py
./rebuilder.py
./scoped_nodes.py
./utils.py
./test/unittest_builder.py
./test/unittest_inference.py
./test/unittest_inspector.py
./test/unittest_lookup.py
./test/unittest_manager.py
./test/unittest_nodes.py
./test/unittest_regrtest.py
./test/unittest_scoped_nodes.py
./test/unittest_utils.py
./test/data/__init__.py
./test/data/all.py
./test/data/format.py
./test/data/module.py
./test/data/module2.py
./test/data/noendingnewline.py
./test/data/nonregr.py
./test/data/notall.py
./test/data/SSL1/Connection1.py
./test/data/SSL1/__init__.py
./test/data/appl/__init__.py
./test/data/appl/myConnection.py
./test/data2/__init__.py
./test/data2/clientmodule_test.py
./test/data2/suppliermodule_test.py
logilab_astng.egg-info/PKG-INFO
logilab_astng.egg-info/SOURCES.txt
logilab_astng.egg-info/dependency_links.txt
logilab_astng.egg-info/namespace_packages.txt
logilab_astng.egg-info/requires.txt
logilab_astng.egg-info/top_level.txt
test/fulltest.sh
test/data/MyPyPa-0.1.0-py2.5.egg
test/data/MyPyPa-0.1.0-py2.5.zip
test/data/__init__.py
test/data/all.py
test/data/format.py
test/data/module.py
test/data/module2.py
test/data/noendingnewline.py
test/data/nonregr.py
test/data/notall.py
test/data/SSL1/Connection1.py
test/data/SSL1/__init__.py
test/data/appl/__init__.py
test/data/appl/myConnection.py
test/data2/__init__.py
test/data2/clientmodule_test.py
test/data2/suppliermodule_test.py
test/regrtest_data/descriptor_crash.py
test/regrtest_data/absimp/__init__.py
test/regrtest_data/absimp/sidepackage/__init__.py
test/regrtest_data/package/__init__.py
test/regrtest_data/package/absimport.py
test/regrtest_data/package/hello.py
test/regrtest_data/package/import_package_subpackage_module.py
test/regrtest_data/package/subpackage/__init__.py
test/regrtest_data/package/subpackage/module.py