Metadata-Version: 1.0
Name: logilab-astng
Version: 0.21.0
Summary: rebuild a new abstract syntax tree from Python's ast
Home-page: http://www.logilab.org/project/logilab-astng
Author: Logilab
Author-email: python-projects@lists.logilab.org
License: LGPL
Platform: UNKNOWN
